pywhiten/PyWhitener.py
pywhiten/__init__.py
pywhiten/cfg/__init__.py
pywhiten/cfg/cfgutils.py
pywhiten/cfg/default.toml
pywhiten/data/Frequency.py
pywhiten/data/FrequencyContainer.py
pywhiten/data/InvalidConstructorArgumentsError.py
pywhiten/data/Lightcurve.py
pywhiten/data/Periodogram.py
pywhiten/data/__init__.py
pywhiten/optimization/Optimizer.py
pywhiten/optimization/__init__.py
pywhiten/optimization/models.py
pywhiten/pwio/OutputManager.py
pywhiten/pwio/__init__.py
pywhiten/pwio/utilities.py
pywhiten-1.1.6.dist-info/licenses/LICENSE
tests/__init__.py
tests/test_Frequency.py
tests/test_FrequencyContainer.py
tests/test_Lightcurve.py
tests/test_Optimizer.py
tests/test_OutputManager.py
tests/test_PyWhitener.py
tests/test_copyconfig.py
pywhiten-1.1.6.dist-info/METADATA
pywhiten-1.1.6.dist-info/WHEEL
pywhiten-1.1.6.dist-info/top_level.txt
pywhiten-1.1.6.dist-info/RECORD
