Metadata-Version: 2.4
Name: pywhiten
Version: 1.1.6
Summary: A python package for conducting Lomb-Scargle based prewhitening of stellar time series. 
Home-page: https://www.github.com/erikstacey/pywhiten
Author: Erik William Stacey
Author-email: Erik Stacey <erik@erikstacey.com>
License: MIT
Project-URL: Homepage, https://github.com/erikstacey/pywhiten
Project-URL: Bug Tracker, https://github.com/erikstacey/pywhiten/issues
Project-URL: Documentation, https://readthedocs.org/projects/pywhiten/
Classifier: Programming Language :: Python :: 3
Classifier: License :: OSI Approved :: MIT License
Classifier: Operating System :: OS Independent
Requires-Python: >=3.7
License-File: LICENSE
Requires-Dist: numpy
Requires-Dist: matplotlib
Requires-Dist: astropy
Requires-Dist: tomli
Requires-Dist: scipy
Requires-Dist: lmfit
Dynamic: author
Dynamic: home-page
Dynamic: license-file
